markdown_converter/__init__.py
markdown_converter/app.py
markdown_converter/cli.py
markdown_converter-0.1.1.dist-info/LICENSE
markdown_converter-0.1.1.dist-info/METADATA
markdown_converter-0.1.1.dist-info/WHEEL
markdown_converter-0.1.1.dist-info/entry_points.txt
markdown_converter-0.1.1.dist-info/top_level.txt
markdown_converter-0.1.1.dist-info/RECORD
