Metadata-Version: 2.1
Name: markdown-converter
Version: 0.1.1
Summary: A Flask-based web service to convert any document/url to Markdown
Home-page: https://github.com/hemanth/markdown-converter
Author: Hemanth HM
Author-email: hemanth.hm@gmail.com
Classifier: Development Status :: 3 - Alpha
Classifier: Intended Audience :: Developers
Classifier: License :: OSI Approved :: MIT License
Classifier: Operating System :: OS Independent
Classifier: Programming Language :: Python :: 3
Classifier: Programming Language :: Python :: 3.6
Classifier: Programming Language :: Python :: 3.7
Classifier: Programming Language :: Python :: 3.8
Classifier: Programming Language :: Python :: 3.9
Requires-Python: >=3.6
License-File: LICENSE
Requires-Dist: flask>=2.0.0
Requires-Dist: flask-cors>=3.0.0
Requires-Dist: markitdown>=0.0.1a3
Requires-Dist: click>=8.0.0
